odoo10_addon_sale_delivery_split_date-10.0.1.0.0.99.dev7-py3.8-nspkg.pth
odoo/addons/sale_delivery_split_date/README.rst
odoo/addons/sale_delivery_split_date/__init__.py
odoo/addons/sale_delivery_split_date/__manifest__.py
odoo/addons/sale_delivery_split_date/i18n/ca.po
odoo/addons/sale_delivery_split_date/i18n/es.po
odoo/addons/sale_delivery_split_date/i18n/it.po
odoo/addons/sale_delivery_split_date/i18n/sale_delivery_split_date.pot
odoo/addons/sale_delivery_split_date/models/__init__.py
odoo/addons/sale_delivery_split_date/models/sale_order.py
odoo/addons/sale_delivery_split_date/models/sale_order_line.py
odoo/addons/sale_delivery_split_date/models/stock_picking.py
odoo/addons/sale_delivery_split_date/static/description/icon.png
odoo/addons/sale_delivery_split_date/tests/__init__.py
odoo/addons/sale_delivery_split_date/tests/test_sale_delivery.py
odoo/addons/sale_delivery_split_date/views/stock_picking.xml
odoo10_addon_sale_delivery_split_date-10.0.1.0.0.99.dev7.dist-info/METADATA
odoo10_addon_sale_delivery_split_date-10.0.1.0.0.99.dev7.dist-info/WHEEL
odoo10_addon_sale_delivery_split_date-10.0.1.0.0.99.dev7.dist-info/namespace_packages.txt
odoo10_addon_sale_delivery_split_date-10.0.1.0.0.99.dev7.dist-info/top_level.txt
odoo10_addon_sale_delivery_split_date-10.0.1.0.0.99.dev7.dist-info/RECORD
