Metadata-Version: 2.1
Name: odoo10-addon-sale-delivery-split-date
Version: 10.0.1.0.0.99.dev7
Summary: Sale Deliveries split by date
Home-page: https://github.com/OCA/sale-workflow
Author: Agile Business Group, Odoo Community Association (OCA)
Author-email: support@odoo-community.org
License: AGPL-3
Platform: UNKNOWN
Classifier: Programming Language :: Python
Classifier: Framework :: Odoo
Classifier: Framework :: Odoo :: 10.0
Classifier: License :: OSI Approved :: GNU Affero General Public License v3
Requires-Python: ~=2.7
Requires-Dist: odoo10-addon-sale-order-line-date
Requires-Dist: odoo10-addon-sale-procurement-group-by-line
Requires-Dist: odoo (<10.1dev,>=10.0)
